{"n0008df":"　滅びの運命にある大陸を守るために、人種や性別の垣根を越えて戦い成長してゆく青春ストーリー。それが乙女ゲーム【ナイツ＆ソード】であった。","n0008z":"　こうして貴族をとっちめて金と海を手に入れたワシらは海賊団と別れ、新たな冒険へと旅立った。","n0014eo":"「都には、あんな別嬪さんがたくさんいるのか？」","n0040dz":"「ここに出たときは砦の正反対にも魔物が出たって連絡が入って、隊長と別れて向かうことになったから。俺が向かった方は難敵ではなかったけど、出たタイミングが最悪だ」","n0057cw":"　別名花の王国と呼ばれるローゼン王国。","n0068y":"　急に言われて、左右の区別ができる人の方が少ない。仁も大多数の方だった。","n0077en":"　火遊びの筈だった別の令嬢に殿方が夢中になった結果、婚約者の方が振られてしまうという事もしばしば起こるらしい。そうなった場合、結婚破棄された令嬢は悲惨な末路を辿るそうだ。","n0082ck":"「今回は特別に食べてあげる。食材への礼儀よ」","n0107db":"「そんなにいて何するわけ！？　え、おれの村、別に女の子、引っ張って行かなくったっていいじゃないか、なんで女も少ない村の若い娘攫って行くんだ」","n0115bw":"　竜樹が辺境伯となったのは、地竜に襲われやすい辺境の地を守るためであり、他国からの侵攻を防ぐためでもある。警備だけしていればいいかといえばそうではなく、領主としての務めもある。学生時代は運動部ではあったが、専攻は理系だ。全く畑違いなうえに世界も違う。配された文官はみな有能であるし、補佐役のルサラシャもよく動いてくれるが、まだまだ仕事をするというよりさせられているとしか思えない現状だった。しかし、本人の評価とは別に、周りの評価はすこぶる良い。理由はわかっている。真樹だ。双子の姉。虹の女神。彼女の助力が大きい。女神力というよりは、彼女のキャリアに助けられている。もちろん、女神の空間にての時間節約も大いに利用させてもらっているのも確かだ。","n0116ev":"　そう一人つぶやいた花嫁の名はルーテシア・ラルジャイルという。男爵家の次女であるルーテシアは、普段は自分の容姿に無頓着だ。それでも、ウェディングドレスというのはやはり特別。純白の花嫁となった自分を見て目を丸くしていた。","n0134el":"別の世界線では暗闇を抜けると、雪国が広がっていたりするようだが、あいにくと現実は厳しい。広がっているのは厳しくも懐の深い雪国などではなく、すべてのものを拒絶しようとするような真っ黒である。","n0141ec":"　それに目敏く気付いたらしいサリーが、残念そうな眼差しをどうにか弱々しい愛想笑いで隠して「……マリアは、別の仕事があるから」と戸惑いがちに呟いた。","n0148cs":"　その場合は、ペンダントをふたつ持つか、指輪やブレスレットなど、別の装飾具に精霊石を埋め込む。","n0151dz":"「一人で別のところでやり直すのは大変だろうけど、どうにかやるしかないのね」","n0153s":"　特別な力などそこにはない。","n0166bk":"　無いことが当たり前となってしまえば、そこに特別な意味など見いだせないのだ。","n0169cv":"　触れられていた手を扇で打ち払い、絶対零度の瞳で離別を宣言し、シャルロットに微笑みかける彼女に妹は。","n0189ej":"「？？？別に無双するな、冒険するなって言ったワケじゃないですよ？『冒険者になれない』って言っただけですよ？」女神は首をかしげながら続けて言った。","n0208i":"　幼い頃は母方の親戚の家で暮らしていたが、高校に上がると同時に別居。今は他人の物になった生まれ育った家がある場所の近くで、寂れたアパートの一室を借り一人暮らし中である。親戚からの少しの仕送りとコンビニのバイト、新聞配達とで、忙しい日々を送りながらも自らの生計を立てている。"}