{"n0008df":"　更には暗殺などの卑劣な調略を基本的には禁止して、礼節を重んじる侯爵家を目指していた。","n0014eo":"　圧倒的な数を前に、ユルドゥスは劣勢となった。だが、ある日奇跡が起こった。","n0068y":"　ピンク色とか、薄ベージュ色とか、なんとなく劣情をかき立てる色合いの力学的高層建築物が天に向かってそそり立っている。","n0107db":"「そこらへんが姉さんが私よりも劣っているって長老たちに言われるところだわ。……彼女はきっと気付いている。たぶん感覚的に気付いているわ。だって最初になんて言ったか覚えている？　姉さん元気って聞いたのよ？」","n0141ec":"　漆黒の隊服に劣らず、黒に近い髪と、深い紺色の瞳が一際目を引く。","n0148cs":"　これにより、一時は、それまで劣勢だったメリシスム共和国が勢いを盛り返した。","n0153s":"　慶諾の言う、あいつとは、恐らく近衛隊長のことだろう。そういえば、慶諾の実家と劣らぬ大貴族だったと朋来は思い出す。","n0163dg":"彼とて決して劣っているわけではない。成績は絶えず上位に食い込んでいるし、魔力も公爵家として十分な資質がある。だが、それでは駄目なのだと自嘲せずにはいられないのは、妹の存在故。","n0166bk":"　この世界の基準から考えれば、向こうの世界で平和ボケてしていた稀花の身体能力など、子どもにも劣るというものでしかない。","n0169cv":"「確かに貴女は私の劣等感を取り除いて下さいましたが、それだけで、あとは遠慮をする振りをしてあれやこれやを強請るばかり。ドレスが破かれた？自分で破いておいてよくそんなことが言えましたね」","n0220bs":"ミリアはそんな暗殺者に思わず笑みを漏らす。自分を組み敷いたまま、決して劣勢にはなっていないその人に対して静かに尋ねる。","n0223ei":"　圭は兄と比べると些か勉強の出来が良くない。それは兄が勉強できすぎ、ということもあるので、圭の成績が悪いわけではないが。圭だって学年全体で見れば確実に上位だ。そんな圭は運動が大の得意である。足は速い、球技だって得意、泳ぐのも得意。それに対し兄は足は速いし、ある程度の運動能力もあるが、それらは圭と比べると些か劣る。もちろん、こちらも授業などではできる方としてみなされるレベルではあるが。うん。私の兄弟ハイスペック。私も足は速いが勉強は兄ほどはできない。これは前世での積み重ねがあるからできるように見えているだけで、実際はそこまで頭は良くない。運動だって普通より上なだけだ。足は妙に速いけど。ちなみに球技はあまり得意ではない。特にサッカー。そして、私と兄が圭と比べて明らかに劣っているのが体力である。圭は外で遊ぶのが大好きな子で、気がつけば走り回っている。朝は走り込みをしている。私と兄はどちらかというと勉強の方に時間を割いているのでそれと比べると運動量が少なく、体力の多さも劣る。","n0228eg":"　それはちゃんと尊重したいし、優劣をつけたいわけじゃない。","n0229y":"エレノアさんに負けず劣らず直球なアーノルドさんの質問に、巫女様が一瞬ビクリと怯えました。","n0284ev":"「人の優劣はテストの点数で決まるわけでは……」","n0310cn":"　食材のような劣化するものはともかく、そうでないものは無理に持ち歩く事もない。","n0316bi":"　ふかふかの絨毯が一面に敷かれた床は静かに歩けば音などしない。リリアナはゆっくりドアに近づいて、侍女が居なくなったことを確認するとベッドに人の厚みほどの膨らみを作り、重いドレスを脱ぎきれいではあるが王女が着るものには劣る素朴なそれに着替える。そして今の時期は使われていない暖炉に近づくと、その横にある本棚の小さな突起を押した。すると、重厚で動くなんて考えられもしないそれが音もなくすうっと人一人分だけ動いた。リリアナはそこに体を入れて翻ると壁の突起を押して本棚を元の様に戻し、暗く湿った細い道を慣れた様子で小走りで抜けた。","n0316dk":"　龍王を貫いていた剣は、抜いた途端にぼろぼろと崩れた。もう随分と劣化が進んでいたため、ここ数年は手足を動かせるようになり、意識もはっきりしていたという。","n0317bh":"　それなのに、この中で間違いなく一番見劣りする俺が主人公の勇者とか、いくら夢だとは言え、ちょっと申し訳ない。","n0317dq":"　――魔石の金属疲労は強大な呪文を符呪していると劣化が発生しやすくなる。魔器に符呪する呪文と同じことで、強大な魔法を動かすためには媒体となる魔石にもそれなりの負担がかかるのだ。"}