{"n0008df":"　一瞬だけ不可思議な表情を浮かべた騎士ラインハルトだったが、納得していつもの勝気な笑みを浮かべる。","n0008z":"「はっはっは、今日も可愛いのう我が愛しのユティ♪","n0014eo":"　しだいに、風が強くなる。途中から馬から降りて歩く。でないと、風の煽りを受けて落馬する可能性があった。","n0040dz":"「ええ。……やりようによっては、キマイラの性質を持った合成獣を作れなくもない、ことかしら。現在じゃただの宝石にしか見えないだろうし、技術もないと思うけど、そんな可能性は考えられるわね」","n0057cw":"　可愛い雑貨が飾っている店先へと二人して向かうと、後から、ルイスとアルフレッドが、ヤレヤレと付いてくる。","n0068y":"　でも仁は、仕草だとか性格だとか……優しさだとか、芯が一本通っているとか、そこがとても可愛いと思っている。","n0077en":"「大丈夫でございますよ、リディアーヌ様。アルベルト様も可愛いと思って下さる筈です」","n0082ck":"　少し垂れ目がちな大きな瞳は薄い新緑色。ふっくらとした桃色の唇は少女のような可憐さを引き出している。肩口からふんわりと流されたプラチナブロンドの髪が優しい光沢を放ち、辺りに照り返す。","n0099ci":"「ああ、可哀想なマティ。泣かないで。僕が必ずあの女を罰するから……!!」","n0107db":"後ろから誰かが数人来るな、と思っていたインユェは、動きを止めた。振り返れば、可憐な少女が立っている。","n0115bw":"「サユをすぐに返してください。あんなに俺の名を呼んでいた。可哀想に」","n0116ev":"　ルーテシアはよく見れば愛らしい顔立ちなのだが、花のように華やかな髪色が多いアルビリオン王国では、焦げ茶の髪の毛はとても地味で、顔立ちの可愛らしさが目立たなくなっている。しかし、ルーテシア自身はそのことを悲観したことは一度もない。","n0134el":"　そこまで考えてようやく問題点に思い至った私は、なかなかに間抜けだと自分のことながら苦笑してしまう。最近こんなくだらないことばかりしているな。私は、ポケットから、本来その魔法回路を作動させるために必要なカギとなる魔法石を取り出した。魔法回路を起動させるためにはそのエンジンが必要となる。これは、奴隷の所有者から継続的に魔力を回収し、契約の魔法を作用させ続けるための特殊な魔法触媒だ。これがないと腕輪には魔力は供給されず、当然魔法回路も起動するわけがない。肝心なものをはめていない。まだ育ち切っていない幼女の奴隷。おまけに主人はほとんど未登録状態、カギをすり替えればまだ上書き可能。それほど状態は良くないとはいえ、利用価値は十分あるに違いない。","n0141ec":"　可愛い、可愛すぎる。こんな妹が欲しい。","n0148cs":"　レオンの手の中には、たくさんの可憐な花が咲いている。","n0151dz":"　私から彼に会いにいくことは不可能に近い。それに、目を悪くしてからここまで整えた家を手放すのは惜しい。ここでいるから、ある程度生活できているのだ。","n0153s":"　年は若いのか。少なくとも年上だろうが不細工だろうが、ハゲとデブは嫌だ。でも、デブは痩せさせればいいし、ハゲは見慣れれば可愛く見えないこともない。ただ、繭を望んだというのだから、優しい人であればいいと思う。","n0163dg":"私は殿下より２歳年上だったため、少し人見知りするエイドリアンが可愛くて仕方なかった。","n0166bk":"「可愛くないやつだ」","n0169cv":"　実際にそんな愚妹を持つ王太子である俺、――ウィズワルド・ドゥユルシス・マヌレール――でさえ、性格さえ直れば可愛げが出てきて、同じ王家の血を引く人間として見直してやってもいいと思うくらいには、妹には興味の欠片もなかったのだが。"}