{"n0040dz":"　攻撃を加えられたアダンクは低くうなり、威嚇を露わにした。","n0057cw":"　ベリーは校長や先生の上を旋回し、威嚇するかのように鳴いた。","n0077en":"　私は冷たく言い放つと、ユーグから離れるため椅子から立ち上がり、離れたベッドへ腰掛けた。これで距離は十分に取れたはずだ。近寄ってくるなと目線で威嚇するが、彼はくつくつと笑うばかりだった。","n0082ck":"　じろりと睨みつけると、顔をしわくちゃにさせる。笑顔のつもりかそれとも威嚇なのか、皺が多すぎて判別が付かない。","n0141ec":"　短いブラウンの髪に、机仕事に属しているとは思えない、威嚇の印象を抱かせるややつり上がった目。懐かない番犬のように愛想なく顰められた表情と、ほどよく鍛えられた細身の腰元には剣がある。","n0344ej":"　余程痛かったのだろう。コルが威嚇するように鳴けば、少し距離を置くために後退りし始まる。","n0372do":"　今、最後の方の「あ」に濁点が付いていたのは、気のせいですよね。愛らしい人好きのする笑顔の向こうに何故か威嚇姿勢のキングコブラの幻影が見えた気がしましたが、これも気のせいでしょう。","n0374et":"　トゥリンクス将軍が真っ先に怒声をあげたけど、ホルバンは歴戦の勇者の威嚇にも動じなかった。大きな手をあごの下で組むと、いたたまれない思いをこめた眼でユートレクトを見た。","n0391dt":"　撫でようとしたら、唸って威嚇するなんて、いい度胸じゃねえか。","n0394ce":"僕らの精霊は怒り、威嚇している。","n0421di":"　その顔に返り血がついている以上、それは威嚇にしかならないのだ、と。","n0474q":"　威嚇はせずに近づき、緊張している風なそのトラ猫の臭いを嗅ぐ。","n0497n":"　靄のように流れるそれではなく、はっきりと形のある天を突く積雲だ。胸が騒ぐ。二頭の鬼が立ち上がり、牙を剥いて威嚇するけど、微妙に尻尾が股の間に納まっている。","n0530z":"・攻撃魔術は威嚇・牽制にとどめ、直接当てないように心がけること。意図的に相手を負傷させた場合は減点・懲罰対象とする。","n0541en":"　だが今までの出来事の証明であるジルと、そしてシェリーが確かにここにいる。シェリーは父が気に入らないのか、威嚇のためにぐるぐると喉を鳴らしていた。","n0576cl":"　力ない威嚇をあっさりとかわされて、追い詰められてしまったわたしは庭へと駆け出した。","n0578bf":"急に大神官の金茶の瞳が強い光を帯びた。私はなぜか肉食獣に威嚇されている気分になった。","n0580z":"　自分たち以外の仲間が捕縛されている姿に男たちは衝撃を受けたようだったが、すぐに声を張り上げて威嚇した。","n0609f":"　後ろへと倒れた義人は脇腹の痛みも忘れ、すぐさま体を起こす。すると、志信を威嚇するように小雪が立ちはだかっていた。","n0611bk":"　彼女の部屋の女官が、ドアを開けた。奥の部屋へゆっくりと足を運ぶ。そこには、ソファーにもたれて床に座り、横に座る２匹の犬をなでている彼女がいた。犬は、低い唸り声を上げこちらを威嚇していたが、彼女がなだめているようで、飛びかかってくることはない。彼女は笑顔でこう言った。"}