{"n0008df":"　これも記憶の全てを思い出した影響かな。","n0008z":"　ちなみに『船幽霊海賊団』が負けたのは、貴族の兵士は空を飛べるから船幽霊の特性の影響を受けなかったからだそうじゃ。","n0040dz":"「ええ。キマイラ自身は自身の毒に耐性があるんでしょうけど、それでも毒を吐き続ける喉を持つ以上、毒の影響で柔らかくなっているのだと思うわ。そしてそこからあなたの持つような剣であれば、正面からなら心臓も貫けるでしょうね」","n0057cw":"　完全に前世のゲームやアニメの影響です。","n0068y":"　仁は右斜め前に首だけをめぐらす。木陰に、なにやら動く影が……。","n0077en":"　庭の端に位置する東屋で蹲っている人影が見えた。声はそちらから聞こえてくる。","n0082ck":"　その影響は至る所に出ている。バルドとみた街の景色も今はもっと酷くなっているのだろう。　","n0107db":"「陪都に着き、輿の中を改めたら……影も形もなかったのです」","n0116ev":"　自然と微笑みながらその様子を見ていたルーテシアの目の前にふっと影が差した。","n0134el":"　瞼が重い。しっかりと眠ったはずだが妙に疲れを感じている。これも先ほどの夢の影響だろうか。私は周囲の状況を確認する。昨日の夜とは大きく異なる光景があった。","n0141ec":"　何度見ても、鏡の中の少女にオブライトの面影はない。","n0148cs":"　加護があるとはいえ、人間であるレオンには、精霊の姿はぼんやりとした影にしか見えないが、それらがくるくると回って楽しそうにしているのは確認できた。","n0151dz":"　私、ミルティアは幼いころの怪我の為に、足が不自由でたち続けることも歩くことも出来ない。そして、視力も非常に弱くなってしまってものの輪郭だけがかろうじてわかる程度だ。調子が悪いとただ、影が蠢いているだけに見えてしまう。　","n0153s":"　茂みの影で世間を知らずに微笑む彼女が、何の魔法の力も知識も持っていないことはすでに王宮中の人間が知っていることだった。ついこのあいだまで、彼女はこちらの言葉と文字を必死で覚えていたことは、女官の間でも話題に上っていた。いったい、何のために呼び出された女神さまなのかと。","n0163dg":"指摘すれば照れたように手で撫で付けていた、決して遠くはない幼馴染みの面影を見つけることが出来ない。","n0166bk":"　ルフェアの影に隠れつつ、目の前にやってきた姫をてっぺんから下まで、稀花はまじましと観察した。","n0208i":"　次から次へと厳正な授業中に席を立つ生徒に怒りを爆発させる教師を横切り、その真木野と呼ばれた青年は、教室を去りゆく直前、振り向きざま軽くウインクして「サヨナラ先生☆」とふざけた言葉だけを残し、何の悪びれもなくすりガラスの窓に映る人影を追って教室を後にした。","n0211do":"ましてやその中でチャンバラでも始めようものならそれを見たエミリオにどんな影響を与えるか…！","n0211y":"　イーリカは広場に設置された噴水が見え、且つ自分の姿が見えないであろう建物の影に隠れ、周囲の女性達のちらちらと盗み見る視線を一切無視して立つ茶髪の青年の姿に溜息をついた。","n0220bs":"暗闇に包まれた寝室で動く影があった。"}