{"n0677cx":"　わざとらしく、ヘインワーズ候の敵愾心を煽ってゆく。","n0733cr":"部屋を出て死を伝えたカイルに、項垂れて嘆きはするものの、敵愾心は見せなかった。","n1037cw":"　今まではただ流されるだけだったクラリッサに、明確な目的ができた、というのも大きいだろう。アンジェリカは、ただただヘレナへの敵愾心だけで体を動かしている気がする。","n1044dc":"　それが誰なのか、私もロルフ様も分からない訳がなくて、ただロルフ様は声の主が意外だった事に驚き、それから瞳をみるみる内に細めて警戒心と敵愾心を露にします。","n1252bb":"「群島地帯に出没する海賊達について。海賊の正体はギブズ族の中でも特に陸の人間に対して強い敵愾心と過激な思想を抱いている一派なのです」","n1253cj":"　融けた氷の横に転がる刀剣を拾い上げながら、フェリクスの背を<ruby><rb>睨</rb><rp>(</rp><rt>ね</rt><rp>)</rp></ruby>めつける、金の髪の男はアウローラの視線に気づき、敵愾心に満ちたほほ笑みを寄越す。傍目にはただの色男にしか見えない笑みを。","n1721cj":"　敵愾心は、執着だった。","n1799dt":"　ソニアと対面して以来、エメルダの心には激しい敵愾心が渦巻いていた。レイン王子を巡る嫉妬だけではなく、潜在的にソニアを嫌っているようだった。もしかしたらジェベラばあさんの意識かな、なんて怖い想像をしてしまった。","n1922dj":"　涙に濡れた不思議な碧眼に、猜疑心や敵愾心は見られない。","n1944ck":"　こうしてエルフの村へ案内された訳だけど、さすがに敵愾心溢れる視線を受け続けるのは堪えた。","n2168dj":"　結果、カナリオは悪役令嬢達から漏れなく<ruby><rb>敵愾心</rb><rp>《</rp><rt>てきがいしん</rt><rp>》</rp></ruby>を持たれている状態であり、その敵愾心を黒色に漬け込まれた彼女達から総当りで襲われるのだ。","n2503u":"　敵愾心を感じつつ、紳士的な態度で苦笑し、謝罪した。","n3009bt":"　皆が見ていたならばしっかりと言い含めておけば……駄目、あの場にどれだけ竜瑙の末連なりがいたのかさえ覚えていない。もし六華に敵愾心を抱く者ばかりだったら？竜瑙を貶めようとする不逞の輩がいたら？","n3092y":"新しい魔物と考えるには、まったく敵愾心が感じられなかった。","n3186dz":"　う～む。人前で何ですかお父様……その発言。それに、レオに敵愾心剥き出しの視線を向けてるし。まだ、お父様は根に持つのか。レオのお陰で助かったんだよお父様……そろそろ認めてよぅ。","n3269v":"だがどうも、カルロスがユーリの字は上手いと誉めたせいで、シャルの敵愾心を燃やす結果になったらしい。","n3814y":"　また、寄付を医療保険と考えれば、良心的なように思える。トレイル先生が教会に対して強い敵愾心を持っているために悪い側面を見てしまっているが、一般的な視点はこうなのだろう。もう一度改める必要がありそうだ。","n4234dr":"　今になって拒絶されるのも複雑だし、敵愾心とか嫌悪感とかその辺がないなら良かった。","n4374cs":"　そしてなぜこの娘は、ミシュリーに対して並々ならぬ敵愾心を燃やしているのだろうか。","n5406ew":"　そりゃ敵愾心を剥き出しにして当然だわな。"}