{"n0372do":"　無表情の下で涎を垂らしている私が、無欲なものですか。しっかりどっぷり食欲に<ruby><rb>塗</rb><rp>《</rp><rt>まみ</rt><rp>》</rp></ruby>れていますよ。しかも前世から。","n0391dt":"　四角い顔の、がっしりした人だった。アメフトとかラグビーとかでもやっていそうな感じ。笑うと爽やかスポーツマン風で、ガチムチ系が好きな人には垂涎モノだろう。","n0421di":"　改めてアントン・レイルノートという男を考えてみると、かなりの優良物件だ。少なくとも、未婚の貴族令嬢からすれば垂涎の的、とさえ言っていいだろう。","n0497n":"　勇気を出して、タクの傍にいる一頭に近付いてみる。口の周りを水でびっちょり濡らして涎（よだれ）と一緒にぶるぶるされるとさすがに悲鳴をあげてしまったけど、悪気がないのが分かるから、そんなに嫌じゃなかった。","n0499ds":"　ただ歯を剥き出しにし、涎をたらして今にも噛み付かんばかりだ。そのさまはまるで獣のよう。精霊の力で人はこんなにも変わってしまうのかと、ぞっとした。","n0541en":"　最初こそ涎まみれにされたものの、そのあとは水浴びに連れて行ってくださったり果てにはドライアドの侍女さえ付けてくださったのだ。","n0609f":"　犬種としてはシベリアンハスキーが一番近いだろうか、黒に近い灰色の毛並みに大型犬らしい体躯。噛み合わせた歯はむしろ牙と評するに相応しく、口元から垂れた涎と低い唸り声が本能的な恐怖を誘う。","n0611bk":"　街へ出た翌日、床に直に座り込み、ソファーを背凭れにしてお茶とケーキをのせた盆を床におき、ケーキを食べる。ジロとチャロは、それを眺めながらジッと待っている。涎を垂らして。もう一匹いたタロは、毒味のせいで亡くなった。チャロも危ない状態になったが、なんとか持ち直してくれた。ただ、チャロはその時の毒のせいで、もう先は長くないらしい。ケーキの残りをフォークに刺して、ジロとチャロに交互に差し出す。待ての体制で座っているのだが、フォークに向かって首が伸びていく様は可愛らしい。こんなふうに犬達と遊ぶことを、シリルは最初こそ叱っていたが、他にさしたる楽しみがない私を可哀想に思ったのだろう。見逃してくれている。流石に、犬達と遊んでて、花瓶やらテーブルが欠けてしまったときには叱られたが。そうやって寛いでいるときに、陛下がやってきた。ずいぶん久しぶりだ。","n0677cx":"　私の実家において機械の掃除機相手に縄張り争いをするぽちの鱗は耐火属性と耐魔防御を持つだけでなく、ドラゴンメイルみたいに全て鱗で作られた鎧だとまず剣が貫けない硬さまで持ってしまう騎士垂涎のアイテムである。","n0692es":"急に酸素を取り込めるようになり、涎を垂らし咳込みながら俺はその場に膝をつく。首を抑え、ゲホゲホと息を吐いて吸いながら視界の隅で今度はヴァルの首を締め付けていた鎖が同じように剣で砕かれていた。","n0722ev":"　憎たらしく思うものの、馬の涎のついた髪では獣臭いと言う言葉は否定できない。ヴァイナスは悔しさからギリッと歯噛みした。","n0734bb":"　眠いが、もう少し先をと限界に挑戦し続けるあまり意味不明の独り言を連発し、ご自慢のヒールを四方八方に誤爆しながら、たらした涎を拭っている。その姿が注目の的になっていることももはや気づかぬまま、レンは１ページ、２ページ進んだ所で睡魔に敗北した。","n0766i":"ホタルの言うとおり、呟きは現実逃避に違いない。目の前にあるドレスの試着という、他の女性達から見れば垂涎ものの重責からの。","n0778u":"　私の二の腕が王子の涎でテラテラし始めた頃、助けを求めてクーさんを見たが、クーさんは私の瞳をじっと見つめるだけだった。","n0980el":"───よくよく見ると、娘は大きな口を丸く開けてすぅすぅと寝息を立てている。ついでに言うなら涎が出ていた。喉の奥まで良く見える。","n1037cw":"　宮廷は魔窟だ。相当な深慮遠謀が渦巻いている。中には地位を金で買う者が出るほど、権力というのは垂涎の物であるのだ。","n1044dc":"　……よく考えれば、旦那様が先に起きていたなら私の寝ている顔を見られたという事では？　ぐっすり寝ていて、涎とか垂らしていたのを見られたら……！？","n1164v":"「違います。三時間ほど前からですよ。フフ…ハナ様って寝顔も可愛らしいですね。涎を垂らしながらスヤスヤと…時間を忘れるほどでした」","n1170ek":"           「          アズハー。僕のあの女子の行いに注意が足りなくてごめんよ…。それにしても、その写真、そんなに気にいってたのか？僕は写真を持てても、爪を立てるか、涎塗れになるかだから、ね。         」","n1252bb":"ソースのかかった肉の塊を見て涎を垂らしているレオナの図太さが羨ましい。リィナの方は狩人と同じ考えなのかあちらも羞恥で頬を朱に染めていた。"}