{"n0008df":" 　レアキャラの入手獲、道中の分岐展開や隠れボイスの確率制度。最後のスペシャル動画を見るために、やりこみ中毒プレイヤーが続出した人気作。","n0014eo":"　二体の獲物が目の前に現れるという、絶好の好機だった。","n0057cw":"　茨がルチアを捕獲し、彼女の自由を奪う。","n0077en":"　弱って行く獲物を前に冷静さを取り戻したアルベルト様は、殺気を解いた。血払いをした剣を鞘へ納める。そして、低いけれどよく通る声を発した。","n0082ck":"　この蜘蛛の作る糸は二種類ある。獲物を捕まえるのはかなり粘着力の強いもので、使えないが、網はまだ粘着力が弱く何度か洗えば使えるようになる。","n0107db":"彼女がいなければ、この船もたちまち壊され、大蜘蛛は獲物を複数手に入れていた事だろう。","n0141ec":"　これまでにあった「気に食わない」と感じる苛立ちや、完璧だと思っていた自分に対して初めて覚えた劣等感。どうして、ヴァンレットに怒る事が多かったのか、どうして自分以外の部隊に、オブライトを獲られたくないと思ったのか……","n0148cs":"　スピリル教を信じるメリシスム共和国の人々は、前回の敗戦の失敗を生かし、補給物資を大量に用意していた。そして、彼らが求める聖地の獲得を目指し、進軍を試みていた。","n0153s":"　その足を狙った投刀を無視して次の獲物にかかろうとして、朋来の兜が反動で宙を飛んだ。","n0163dg":"だが、これほどの魔力持ちならば、確かに王子が食指を覚えるのも仕方がないと思えた。何しろ、魔力溢れる者同士の性行は、この上なく甘美である。互いの魔力が交じり合えば、魔力酔いが媚薬のような効果をもたらすのだ。ガイヤ王子と引けを取らない相手を探すのは難しく、だからこそ、目の前の少女は———今の瞬間、獲物認定されたに違いない。","n0211y":"　面白い物見たさに運動不足にぜーはー言いながら、三階へと上がるってパラスの教室のあたりを見れば、後少し、という所で捕獲に成功されている姿だった。","n0223ei":"　結局あのままゴールまで一直線に走り抜け、私は、いや、赤坂は一位を獲得した。そしてそのまま保健室行き。","n0228eg":"「魔獣は人間より脂肪が多いので、刃がすぐにだめになり、切るのが難しくなるのです。このスキルがあれば、単身で乗り込んでも、刃がだめになることがなく、ただひたすらに目の前の獲物を切るだけで済みます」","n0242w":"　他人の恋愛話に花を咲かせたことのないアレンは、二人にとって極上の獲物だったようだ。","n0274bk":"「ある朝、雨が止んで、晴れ間がのぞいた。村の猟師が、２日前に仕掛けたわなを見に山へ出かけた。小さな獲物用に仕掛けたわなだから、仲間と出かけずに一人で見に行ったんだ。少しでも晴れてる間に仕事をしようと思ったから」","n0284ev":"「それは暗殺者のレベルが低かったからだろう？　あと獲物がなまくらだった」","n0310cn":"　ついでに、悪意があった場合は、防御でなく捕獲に変えておいた。","n0317dq":"　まるで飢えた狼が獲物を貪るように、ユーリは溜め込んだパトスをレイラに流し込んでくるのだ。","n0339dn":"　テレーゼは目の前の箱を見つめ、中身を想像する。そういえば昔、弟のエリオスが「僕からのプレゼントです」と言って、こんな感じの箱を渡してきたことがある。中身は元気いっぱいの獲れたてイモムシだった。","n0344ej":"　床に厚手の絨毯を敷き、壁に背を凭れ掛かるようにして座り、静かに獲物が罠にかかるのを待っている。"}