{"n0169cv":"　嫌われているんだ、憎まれているんだと思われていた、と心情を涙ながらに吐露する姿は、心に疚しいものを持つ者へ確実に杭を打ち込んだのが解った。","n0223ei":"「委員長とは友達だし。疚しいことないし、堂々としてればいいと思うんだよね」","n0310cn":"「そうよ。疚しいことがないなら、雇えるはずでしょ」","n0541en":"　グリードに仕えたいという気持ちには一辺の疚しさもないのに、いったいどう言えばこの気持ちを証明できるのか。","n0880dy":"「ここで欠席なんてしてみなさい。疚しいことがあると、噂を肯定することになりますからね。それと、今後一切、ルゼール卿とは会わないこと。もしどこかの場で会うことがあっても、挨拶以上の接触は認めませんからね」","n0924cf":"「疚しい気持ちがあるなら関係ありません」","n0988cb":"　こうして有理子が本来の目的に身が入らぬまま考えを巡らせるうちにも、義希は転々とナンパをしては女性と２人で店に入り、最終的に店の前で別れることを繰り返した。かと言って特別疚しい店に入るわけでもなく、不可解な彼の行動に有理子と蒼は顔を見合わせて首を傾げるのだった。","n1044dc":"「……えーと、その傷はちょっと見せてくれる事って出来る？　あ、いや疚しい気持ちとか全くなくて、診察って意味でだよ」","n1781cq":"疚しいことでもあるのか、すいっと顔を逸らされる。","n1913dr":"　しかし、游峯も一緒で、何も疚しいことはしていない。ただ、一緒に眠っているだけだと説明すると、渋々許してくれた。","n2503u":"　疚しい事があるように、すぐに視線を逸らしたトリプトルに、トロイは項垂れる。","n2517x":"　別に疚しいことはしていないけど、確かに、その点について神殿の人たちが警戒しても仕方ないと思う。","n2804r":"　だって、何も疚しいことなんてない。ただ、魔獣として転生したのに、ファラティアとしての記憶が蘇ってしまっただけだ。","n3009bt":"「再度申し上げましょう。澳篭がお嬢様について隠し立てせねばらならい、疚しさなど一切ございません。まして尊き一華、竜瑙より事隠すなど……従家筆頭たる澳篭を愚弄するだけならばまだしも我らがお嬢様の御心を乱すとあらば、四の侍女として覚悟を決めさせて頂く」","n3033ef":"「少し、彼女の相談に乗っていただけだ。疚しいことは何もない」","n3079o":"「別に何も。何かを感じるというのなら、それはあなたの疚しさですね」","n3186dz":"「――アレク様？なんで顔逸らすんです？何か疚しいことでもあるんですか？」","n3244cr":"勿論疚しいことは数え切れないほどしてきたが、結婚を機に派手な私利私欲に走ることは控え身辺を整理していた。","n3269v":"だがこう、具体的な匂いといった痕跡がある訳ではないし、疚しい方向に思考が滑ったから驚いただけであって。単にユーリが長距離を移動したせいで体が埃っぽいと感じ、シャルに体を拭いて貰っていただけ、というような、何でもないオチに違いない。","n3397x":"決してこの疚しい心を悟られないように。"}