{"n1944ck":"　今までの砥石では、逆に石の方が削れてしまう。","n2499j":"　幸助がみつけたのは、砥ぎ師からの依頼だ。研いでもらいたいという依頼ではなく、忙しいので伝票整理や客の対応をお願いしたいといった内容だ。いくら忙しいといっても素人に砥ぎを任せはしないだろう。あと前提条件として文字の読み書きができること、とったものがあった。このことからも雑務をしてほしいのだとわかる。","n3202q":"シリウス「あぁ、包丁を砥いでいたんですね」","n3457ca":"　よく砥がれた刃が、部屋の灯りを受けて光る。","n4054cx":"「沢山買ったオマケだ。これも持ってけ。野外で使う用の砥石だ。切れ味が悪くなったらコレで研げ。んで、帰ったらすぐに修理に出せ。いいな。鈍らのまま使うなよ？」","n4084cc":"「これは投擲用だからな、砥石はいらないだろ。使い捨てだと思って使うんだぞ」","n4378dx":"　砥石で研ぎまくり、小さく細く、なったもの。","n4410bb":"ガッシガッシガッシガッシ……「くそう、地味だ……。そしてなんだか<ruby><rb>山姥</rb><rp>（</rp><rt>やまんば</rt><rp>）</rp></ruby>が夜中に包丁砥いでるみたいだ……。自分で言っててへこむわぁ。まだ２７歳独身だよ？　山姥て。つか、ひとりごと言ってる時点でかなりアウトかもしれない……」ブツブツ……","n5370em":"　ベルは剣を買ったのに砥石を持っていない。","n6615m":"　髪も灰色で全体的に色素が薄い印象も、鋭く砥がれた刃を連想させてしまうのかもしれない。","n6888cb":"　代わりに脳裏に描くのは、つい二時間ほど前に別れた、愛しい恋しい少女の姿。――全く、彼女に教わった知識は、砥げば砥ぐだけ鋭い武器になってくれる。","n7359s":"「カスパルさん、ちょうど探していたんですよ。この前言ってた鋸と砥石、それから<ruby><rb>鑿</rb><rp>（</rp><rt>のみ</rt><rp>）</rp></ruby>仕入れてきたんですけど、見てもらえますか？」","n8507bm":"そういって砥粉色の紙を手渡された。間違いなくティアの字だ。","n8893z":"ぎょっとしたが砥石があったため、包丁を砥いでいたのかと胸を撫で下ろす。","n0153k":"　静かに言うと砥石を用意して包丁を研ぎ始めた。","n0637ew":"日向は軽く居間の掃除を行い、とりあえずと米砥ぎし炊飯器のタイマーを起動させておく。","n0685x":"　シャープニングにはシャープニングオイル（潤滑油）とシャープニングストーンと呼ばれる砥石を用いて手で刃の角度に沿わせて丁寧に研いでいくのである。","n0690cw":"漆黒の髪は二つに結われ、彼女は砥がれた日本刀のように、見る人を魅了するような微笑みを浮かべていた。その背景と化している車の前では、執事である国枝さんが頭を抱えている。","n4923bt":"　匙を卵粥の中に入れ、掬い上げそれを口に含んだ。温かいおかゆと砥いだ卵の味が、舌の上に広がる。","n8888cq":"「大見さん、お米をそんなに神経質に砥がない方が、今のお米はおいしいんです」"}