{"n0008df":"『どんな窮地、死ぬ刹那までも冷静沈着に』","n0014eo":"「窮屈なの、嫌いなんだよ」","n0040dz":"　答えに窮していると、イオスはゆったりと続けた。","n0068y":"　クレアさん一人でどうやってこの窮地を切り抜けようというのか？","n0115bw":"　ある時、自分の力を試すための行為が、黒騎士を窮地に追いやった。彼も地竜と同じく地脈に由る者、竜とともに葬るところだったのだ。彼を救ってくれた彼の双子の姉に泣いて詫び、もう二度としないと誓った。","n0141ec":"　それは勘弁願いたい。窮屈で堅苦しい貴族の世界は性に合わない。","n0163dg":"相次ぐ天候不順に飢饉が起こり、貧窮した民の不安は、魔物の横行という負の連鎖により爆発した。街は荒れ、盗人が増え、略奪が行われるようになった。それを取り締まるべき騎士は討伐隊へ人員を割かれていたため、街の治安維持が後手に回ったことで、暴動が起こったのだ。","n0166bk":"　この暗黒大神官こそが窮地に対する切り札になるのだと、稀花は必死で下手に出た。","n0223x":"　背中が寒い。コルセットがきつい。上げ底された胸が窮屈。不躾に寄せられる視線が不愉快。どれもこれもすべてあの胡散臭い神官さまのせいに違いない。","n0284ev":"　魔王に捕らわれているアリシアは、答えに窮するエドウィン王子を見て取り乱す。","n0310cn":"　困窮した様子がないことが一番の理由だと思いますが、カグラ様は無理や無茶をなさいません。","n0317dq":"「分からない？　窮屈だって感じたことない？　今の世の中」","n0344ej":"「前から言っているが、グレーニャ様だってライナスの現状を望んでいないって。お前は過去に縛られ過ぎて窮屈になっているから、自由になって身軽になるべきだ。リーフデみたいに自由になっては駄目だが」","n0364cx":"　白を基調としたこの神秘の空間は、シェリアにとってはもっとも居心地のいい場所のひとつだ。祝福の間は、真っ白すぎて逆に少し窮屈だった。","n0372do":"　前世は彼氏いない歴イコール年齢の、ややぽっちゃり（自己診断）享年２８歳歯科衛生士でした。ようやく女の園な仕事にも、可愛らしくて腹回りと肩回りが窮屈な制服にも慣れて、何人かの同僚の寿退社を見送って・・・という仕事帰りに、猫をよけて車の単独事故にて死亡。迫る電柱にあっと思ったのは覚えていますが、痛みは覚えていません。","n0374et":"　だから、遠慮なく言わせてもらったのだけど、東１９番街の窮状を今朝聞いたばかりだったから、その気持ちは余計に抑えることができなかった。","n0391dt":"「私がですかぁ～？　どうでしょう～？　カトリーナ様を見ていると、窮屈そうですわぁ～。お供となると、さらに大変そうです～。どちらかと言いますと、傍観している方が楽しそうですよねぇ～」","n0421di":"　そんな絶対的な窮地に、動くことができない。","n0486y":"　心配されることへの窮屈さと、喜び。複雑な感情の中で、彼なりに一人で前に進もうとしているのだろう。ミシャにも覚えがある感情だ。嬉しいけどそれが、時々わずらわしい感じ。","n0497n":"　策謀の渦巻く宮廷にあって、誤解を招くほど飾り気のない王子に仕えるのはさほど苦ではないが、城勤めはやはり窮屈だった。自分自身を戒めるためにも、俺はあの荒野に出掛けるのが日課になっていた。"}