{"n0008df":"　騎士には襲来する<ruby><rb>妖魔</rb><rp>（</rp><rt>ヨーム</rt><rp>）</rp></ruby>の群れとの実戦でしか会得できない経験値もある。","n0014eo":"　羊の群れと毒蛇が出会ってしまい、統率が崩れることも多々あったのだ。","n0057cw":"　順位が張り出される食堂件大広間は、生徒達が自分の順位を確認する為に群がっていた。","n0068y":"　金獣の大群を向こうに回し――。","n0077en":"　行動力抜群の彼女からは逃げきれず、説明する前に出会ってしまった訳か。　私は、彼の行動に納得した。","n0107db":"蟲を捌く。それが第一だ。そうしないと掃除屋たちが死肉に群がって来ると知っている。","n0141ec":"　下心がないリリーナの無邪気な笑顔は、破壊力抜群だ。","n0148cs":"　火属性は赤茶、水属性は群青、風属性は薄緑、地属性は黄土――そして、どの属性の精霊にも語りかけられるのが、虹色だ。","n0163dg":"驚愕に戦く教師群を尻目に、エミリアは歌うように其々の魔族と契約を交わす―――これは、未だに語り継がれる珍事である。","n0166bk":"　しっかり綿を詰め込んだおかげで、ふかふか感は抜群だ。","n0189ej":"朝起きて外を見ると、そこには地平線を埋め尽くすパーティーメンバー希望者の群れが待っていたのだった。","n0208i":"　はっきり言って頭に何が詰まっているのか分からないぐらい勉強は出来ないが運動神経は抜群。バスケ部に所属しエースと謳われている典型的なスポーツ馬鹿だ。","n0223ei":"　とりあえず心を落ち着かせるためにクラス表とその周りに群がる同級生たちを少し離れたところから写真に収めた。","n0228eg":"　やっぱり包丁の切れ味は抜群で、数枚重ねたバジルも繋がることなく、あっさりと切り離された。","n0242w":"　ちなみによく一緒に演習もする。とはいえ、全体的に爽やかなディディエの師団と、男臭さ抜群なアレンの師団では、醸し出す雰囲気が全く違うので、アレンは時折切なくなる。","n0284ev":"「バルシャイン王国が成立する以前は、ここら一体は群雄割拠の戦国時代だった。そこで戦に連戦連勝し、国を作ったのがバルシャインの初代国王だ。彼には優秀な部下が二人いた、光魔法の使い手と闇魔法の使い手だ」","n0310cn":"　少し踏み込んで調べてみると、森に近い辺りに、竹が群生している。","n0317dq":"　立派な赤のマントに金の刺繍が栄えている。着ている服装は群青色の上着だったが、こちらも装飾とフリルが散りばめられていて、高貴な人なのだろうと簡単に推測できた。そんな彼の後ろ頭を見上げると、美しい白銀の髪がさらさらと煌めいているのが見えた。","n0339dn":"（なんというパンチ力！　敬語抜きのジェイド、破壊力抜群だわ！　これじゃあ、いつかやられてしまう……！）","n0344ej":"　これは早々にリーク元を確認しなければ！　と、私は意気揚々と人々の群れへと向かう。"}