{"n0014eo":"　リュザールは茜色に染まる草原に池を発見し、その場を野営地と決めた。","n0040dz":"　ドアをしめて部屋に足を進めたイオスはそのまま窓辺までまっすぐ歩き、茜色に色づき始めた空を見上げた。","n0057cw":"　茜色の空に舞い上がって行き、羽を大きく広げると今度は水竜になり地上に舞い降り、そこからアカシアの木が生えた。","n0107db":"雪が降っていた。雪は湯気の立つくれないに溶けていき、茜はさらに際立った。","n0134el":"　天気は良好。茜に染まった空がだんだんと東から、優しい藍色へと変わっていく。原風景といえるような景色でありつつも、どこか神秘的だ。問題点は一つ、私が最低な気分にあるということだけだ。","n0148cs":"　植物の浮き彫り細工が施された茜色の扉を押し開くと、礼拝用の長椅子が並ぶ教会内部が見えた。","n0223ei":"「茜、挨拶しなさい」","n0372do":"　そういえばこの兄妹、セバス族と言って文武両道で、仕える主を決めると一生忠誠を誓うという、有名な部族らしい。茜色の瞳が特徴で、彼らを侍らせるのは、一種のステータスなんだとか。いい拾い物をしましたが、初見で一生とか重すぎます。","n0497n":"「ほんまか？　偽物じゃないよね？」と疑いの眼差しを向けるのは、短髪ヤセ眼鏡の白沢茜。","n0612ca":"この部屋に入った当初は天頂にあった陽が、茜色を帯びるほど長い間、リーネンはカティーバの話を聞き、そして考えていた。","n0677cx":"　夕暮れ時によって茜色に染まる教室内でイケメンが私に向かって頭を下げる。","n0733cr":"色白で、緩くウェーブを描く柔らかそうな栗色の御髪に、ぱっちりとした二重の茜色の瞳。桜色に艶めくふっくらとした唇。","n0980el":"　傾いた陽が徐々に茜色に変わり行く城門で、ヴォルデマーはミリヤムを見送った時と同じ様にその内に立っていた。","n0988cb":"　さて、妖精の意思として残されていた大斧「アネモネ」は、元の名を「茜」と云った。更には、ある特殊な能力を持つ家系の末裔だと語る。","n1075co":"　涙目で下を向いたせいで、茜色のドレスの膝に、ぽつりぽつりと涙が落ちて滲みをつくる。","n1230ei":"　領内に入る頃には、太陽はゆるやかに下り始めていた。万一見張りがいたら困るので、港に続く手前の道で馬車から降りる。空はぼんやりと茜色が滲み始めていたが、係留施設ではいまだ到着した船から荷を下ろす者や、運ばれてきた荷物を検品する者の姿がある。","n1253cj":"　薄めた茜色に染まりゆく回廊に、ふたりの長い影とのんびりした足音がカツン、カツンと響き渡った。思いつめたように口を引き結び、すがるような目を向けるフェリクスの頭を、センテンスはガシガシと、己の頭にするように撫で回した。","n1266de":"　ルークに誘われて王族居館にある庭園を散歩をしている。セシルの歩くペースに合わせてエスコートする彼は、やっぱり王子さまだ。庭師に丁寧に整えられた庭園を夕日が茜色に染めて、ルークに触れている腕のぬくもりと共にセシルを温かく包んでくれる。","n1672bt":"　今は茜色の混じった青空ではあるが。","n1841o":"　空から降り注ぐ光は徐々に赤い衣を纏い、昼と夜は茜色の濃淡をもって入れ替わる。"}