{"n0008df":"　断末魔を叫ぶ間のもなく<ruby><rb>妖魔</rb><rp>（</rp><rt>ヨーム</rt><rp>）</rp></ruby>は次々と散る。ベルガの振るう鉄塊のような大剣によって。","n0014eo":"　火を消して、大きな丸い鉄板を裏返したものを被せた。これに、フェルトを被せたらあっという間に調理場が食卓となる。ここに、作った料理を並べた。","n0040dz":"　引き受けた怪我が、その場で修復されていく――それが、激しい痛みを訴えている。長年の生活で痛覚はだいぶ鈍っていると思っていたが、体が引きちぎられるような痛みを気のせいにすることなどできなかった。口の中には鉄の味が感じられる。","n0068y":"　遠隔操作された鉄人の様に、ギコギコした動きでチビッコを降ろす。チビッコは四つんばいで毛をプルプルさせた。","n0077en":"　一方的に私のことを知っていたり、含みのある言い方をされた事に疑問を感じたが、私はドレスをつまんでお辞儀をした。勿論、顔には鉄壁の微笑を湛えている。","n0107db":"「これはね、蟲殺しの石なんだよ。あんたの鉄の刃物くらいだったら、余裕で切り飛ばせる。鋭いのに、蟲の体液でも切れ味が落ちない。蛞蝓鬼程度の粘液で、切れなくなるやわな武器じゃないんだよ」","n0134el":"　鋼鉄の板で灰をすりつぶされてしまったかのように胸が厳しい。息ができなくなり、さっと全身から血の気が引いていく。やめてくれ、そんな目で私を見るな。私は後ずさる。それに続くように少女はこちらに向かって一歩、距離を詰めてくる。","n0141ec":"　まさに、鉄壁の要塞。","n0148cs":"　小さく切った生地を、紙を敷いた鉄板の上にのせ、加熱箱の中に入れる。","n0153s":"　羅心が王様に繭のことを告げ口しているのは百も承知だし、まさかあの鉄面皮がこんな御茶会にのこのこ出てくるとも思っていない。","n0163dg":"粗末な一室の、鉄格子で遮られただけの空間で、薄暗い中、真っすぐにこちらを見つめている姿は、まるで王宮で対面しているような錯覚を味わう。","n0166bk":"　稀花はあっさり開いた鉄格子のせいで、地面に顔面から勢いよく突っ込んだ。","n0228eg":"「草だけじゃなく鉄も好きなのか？」","n0229y":"「何て言ったと思う？『貴女の様な無鉄砲で後先考えず粗野な振る舞いをする女が居るから、巫女様の様な純真な御方が謂われのない誹謗中傷を受けるのです。』…だってさ！――あ、今のモノマネ結構似てなかった？」","n0242w":"　助けを求めても、フェルナー卿はそっぽを向いてニヤニヤしているだけで、全くもって頼りにならない。グルだ、これは完全にグルだ。アレンはだらだらと冷や汗を流しながら、四面楚歌の状況に嘆息しつつ、鉄壁の理性を総動員して懸命に馬を進めた。","n0284ev":"　ゲームではレベル上げならドルクネスの闇ダンジョン、装備集めならバリアスのダンジョンが鉄板であった。装備の性能はランダムなので、欲しい属性と付与効果が一致するまで周回するのだ。","n0310cn":"ハーフエルフ。森の国の元王女と転生者の子供。ランスの商業ギルドのギルドマスター。すらりとした体格のエルフらしい美形。ただし、鉄仮面。あまり表情が動かずわかり辛い。有能で冒険者としても一流（Aランク）","n0316bi":"　ギルバートはリリアナを安心させるように鉄仮面のような固い表情を僅かに目元だけ緩めて笑ってリリアナの頭を撫でた。そしてそれだけ言うと、兄は慌しく部屋を出て足早に去っていた。多忙な彼はこの後も予定が詰まっているのだろう。フォンディアは王政であるが、現在は王であるフェルディナンはほとんど引退していると言っても過言ではない。成人し、優秀な兄が執務の中心にいる状態なのである。その兄は当然多忙でいつも何かの書類を片手に持っている。","n0317dq":"　環境は厳しいものだったが、希少な鉱脈がいくつも見つかり、鉄と銀、鍛冶と武器の国として栄えることができた。","n0339dn":"　下方からの、しかもよくも狙いを定められていない攻撃とはいえ、侍女の方も完全に不意打ちを食らっていた。腹をえぐるような肘鉄を食らった侍女が仰向けに仰け反り、蹈鞴を踏んでいる。"}